cchdo/hydro/__init__.py
cchdo/hydro/__main__.py
cchdo/hydro/__main_helpers.py
cchdo/hydro/accessors.py
cchdo/hydro/checks.py
cchdo/hydro/conformance.py
cchdo/hydro/consts.py
cchdo/hydro/convert.py
cchdo/hydro/core.py
cchdo/hydro/dt.py
cchdo/hydro/flags.py
cchdo/hydro/migration.py
cchdo/hydro/py.typed
cchdo/hydro/rename.py
cchdo/hydro/sorting.py
cchdo/hydro/tutorial.py
cchdo/hydro/types.py
cchdo/hydro/utils.py
cchdo/hydro/exchange/__init__.py
cchdo/hydro/exchange/exceptions.py
cchdo/hydro/exchange/helpers.py
cchdo/hydro/legacy/__init__.py
cchdo/hydro/legacy/coards/__init__.py
cchdo/hydro/legacy/coards/name_netcdf.csv
cchdo/hydro/legacy/woce/__init__.py
cchdo/hydro/legacy/woce/woce_params_for_exchange_to_woce.csv
cchdo/hydro/tests/__init__.py
cchdo/hydro/tests/conftest.py
cchdo/hydro/tests/test_accessors.py
cchdo/hydro/tests/test_checks.py
cchdo/hydro/tests/test_core_ops.py
cchdo/hydro/tests/test_csv.py
cchdo/hydro/tests/test_exchange.py
cchdo/hydro/tests/test_legacy.py
cchdo/hydro/tests/test_merge.py
cchdo/hydro/tests/test_rename.py
cchdo/hydro/tests/data/33RR20080204_mini_hy1.csv
cchdo/hydro/tests/data/__init__.py
cchdo/hydro/tests/data/btl_csv.csv
cchdo/hydro/tests/data/btl_time_span.csv
cchdo/hydro/tests/data/merge_placeholders.csv
cchdo/hydro/tests/data/stns_test_data.json
cchdo_hydro-1.0.2.15.dist-info/licenses/LICENSE.md
cchdo_hydro-1.0.2.15.dist-info/METADATA
cchdo_hydro-1.0.2.15.dist-info/WHEEL
cchdo_hydro-1.0.2.15.dist-info/entry_points.txt
cchdo_hydro-1.0.2.15.dist-info/top_level.txt
cchdo_hydro-1.0.2.15.dist-info/RECORD
